r_repeat/__init__.py
r_repeat/main.py
r_repeat-0.3.7.dist-info/METADATA
r_repeat-0.3.7.dist-info/WHEEL
r_repeat-0.3.7.dist-info/top_level.txt
r_repeat-0.3.7.dist-info/RECORD
