Metadata-Version: 2.1
Name: r-repeat
Version: 0.3.7
Summary: Create a palette preview image by using a simple config file
Home-page: https://github.com/Aonodensetsu/r_repeat
Author: Remigiusz Dończyk
Author-email: donczyk.remigiusz@gmail.com
License: GPL-3.0
Keywords: repeat,probability,random
Classifier: Development Status :: 5 - Production/Stable
Classifier: Intended Audience :: Developers
Classifier: License :: OSI Approved :: GNU General Public License v3 (GPLv3)
Classifier: Operating System :: OS Independent
Classifier: Programming Language :: Python :: 3.10
Classifier: Topic :: Software Development :: Libraries :: Python Modules
Classifier: Typing :: Typed
Requires-Python: >=3.10
Requires-Dist: tqdm
